qtools/__init__.py
qtools/garbagecollector.py
qtools/tasks.py
qtools/utils.py
qtools/qtpy/__init__.py
qtools/qtpy/binding_helper.py
qtools/tests/__init__.py
qtools/tests/test_app.py
qtools/tests/test_tasks.py
qtools-0.1.2.dist-info/DESCRIPTION.rst
qtools-0.1.2.dist-info/METADATA
qtools-0.1.2.dist-info/RECORD
qtools-0.1.2.dist-info/WHEEL
qtools-0.1.2.dist-info/metadata.json
qtools-0.1.2.dist-info/top_level.txt
