Metadata-Version: 2.0
Name: qtools
Version: 0.1.2
Summary: Python tools for Qt.
Home-page: https://github.com/rossant/qtools
Author: Cyrille Rossant
Author-email: rossant@github
License: LICENSE.md
Platform: UNKNOWN
